[
    {
        "id": 10,
        "name": "2022-07",
        "expenses": {
            "id": "2022-07-Expenses",
            "expenses": [
                {
                    "id": 1,
                    "name": "rent",
                    "value": 700.12
                },
                {
                    "id": 2,
                    "name": "food",
                    "value": 300.03
                },
                {
                    "id": 3,
                    "name": "electricity",
                    "value": 50
                },
                {
                    "id": 4,
                    "name": "rent",
                    "value": 700
                },
                {
                    "id": 5,
                    "name": "food",
                    "value": 300
                },
                {
                    "id": 6,
                    "name": "electricity",
                    "value": 50
                },
                {
                    "id": 7,
                    "name": "rent",
                    "value": 700
                },
                {
                    "id": 8,
                    "name": "food",
                    "value": 300
                },
                {
                    "id": 9,
                    "name": "electricity",
                    "value": 50
                },
                {
                    "id": 10,
                    "name": "rent",
                    "value": 700
                },
                {
                    "id": 11,
                    "name": "food",
                    "value": 300
                },
                {
                    "id": 12,
                    "name": "electricity",
                    "value": 50
                },
                {
                    "id": 13,
                    "name": "rent",
                    "value": 700
                },
                {
                    "id": 14,
                    "name": "food",
                    "value": 300
                },
                {
                    "id": 15,
                    "name": "electricity",
                    "value": 50
                },
                {
                    "id": 16,
                    "name": "rent",
                    "value": 700
                },
                {
                    "id": 17,
                    "name": "food",
                    "value": 300
                },
                {
                    "id": 18,
                    "name": "electricity",
                    "value": 50
                },
                {
                    "id": 19,
                    "name": "electricity",
                    "value": 50
                },
                {
                    "id": 20,
                    "name": "electricity",
                    "value": 50
                },
                {
                    "id": 21,
                    "name": "electricity",
                    "value": 50
                },
                {
                    "id": 22,
                    "name": "rent",
                    "value": 700
                },
                {
                    "id": 23,
                    "name": "food",
                    "value": 300
                },
                {
                    "id": 24,
                    "name": "electricity",
                    "value": 50
                },
                {
                    "id": 25,
                    "name": "electricity",
                    "value": 50
                },
                {
                    "id": 26,
                    "name": "electricity",
                    "value": 50
                }
            ],
            "total": 1250
        },
        "incomes": {
            "id": "2022-07-Incomes",
            "incomes": [
                {
                    "id": 1,
                    "name": "job1",
                    "value": 2000
                },
                {
                    "id": 2,
                    "name": "sales2",
                    "value": 300
                },
                {
                    "id": 3,
                    "name": "job3",
                    "value": 2000
                },
                {
                    "id": 4,
                    "name": "sales4",
                    "value": 300
                },
                {
                    "id": 5,
                    "name": "job5",
                    "value": 2000
                },
                {
                    "id": 6,
                    "name": "sales6",
                    "value": 300
                },
                {
                    "id": 7,
                    "name": "job7",
                    "value": 2000
                },
                {
                    "id": 8,
                    "name": "sales8",
                    "value": 300
                },
                {
                    "id": 9,
                    "name": "job9",
                    "value": 2000
                },
                {
                    "id": 10,
                    "name": "sales10",
                    "value": 300
                },
                {
                    "id": 11,
                    "name": "sales11",
                    "value": 300
                },
                {
                    "id": 12,
                    "name": "sales12",
                    "value": 300
                },
                {
                    "id": 13,
                    "name": "sales13",
                    "value": 300
                }
            ],
            "total": 2000
        },
        "stats": {
            "id": "2022-07-Stats",
            "available": 400,
            "withGoal": 300,
            "saved": 400,
            "goal": 45,
            "savings": 3000
        }
    },
    {
        "id": 11,
        "name": "2022-06",
        "expenses": {
            "id": "2022-06-Expenses",
            "expenses": [
                {
                    "id": 1,
                    "name": "rent",
                    "value": 700.12
                },
                {
                    "id": 2,
                    "name": "food",
                    "value": 300.03
                },
                {
                    "id": 3,
                    "name": "electricity",
                    "value": 50
                },
                {
                    "id": 4,
                    "name": "rent",
                    "value": 700
                },
                {
                    "id": 5,
                    "name": "food",
                    "value": 300
                },
                {
                    "id": 6,
                    "name": "electricity",
                    "value": 50
                },
                {
                    "id": 7,
                    "name": "rent",
                    "value": 700
                },
                {
                    "id": 8,
                    "name": "food",
                    "value": 300
                },
                {
                    "id": 9,
                    "name": "electricity",
                    "value": 50
                },
                {
                    "id": 10,
                    "name": "rent",
                    "value": 700
                },
                {
                    "id": 11,
                    "name": "food",
                    "value": 300
                },
                {
                    "id": 12,
                    "name": "electricity",
                    "value": 50
                },
                {
                    "id": 13,
                    "name": "rent",
                    "value": 700
                },
                {
                    "id": 14,
                    "name": "food",
                    "value": 300
                },
                {
                    "id": 15,
                    "name": "electricity",
                    "value": 50
                },
                {
                    "id": 16,
                    "name": "rent",
                    "value": 700
                },
                {
                    "id": 17,
                    "name": "food",
                    "value": 300
                },
                {
                    "id": 18,
                    "name": "electricity",
                    "value": 50
                },
                {
                    "id": 19,
                    "name": "electricity",
                    "value": 50
                },
                {
                    "id": 20,
                    "name": "electricity",
                    "value": 50
                },
                {
                    "id": 21,
                    "name": "electricity",
                    "value": 50
                },
                {
                    "id": 22,
                    "name": "rent",
                    "value": 700
                },
                {
                    "id": 23,
                    "name": "food",
                    "value": 300
                },
                {
                    "id": 24,
                    "name": "electricity",
                    "value": 50
                },
                {
                    "id": 25,
                    "name": "electricity",
                    "value": 50
                },
                {
                    "id": 26,
                    "name": "electricity",
                    "value": 50
                }
            ],
            "total": 1250
        },
        "incomes": {
            "id": "2022-06-Incomes",
            "incomes": [
                {
                    "id": 1,
                    "name": "job1",
                    "value": 2000
                },
                {
                    "id": 2,
                    "name": "sales2",
                    "value": 300
                },
                {
                    "id": 3,
                    "name": "job3",
                    "value": 2000
                },
                {
                    "id": 4,
                    "name": "sales4",
                    "value": 300
                },
                {
                    "id": 5,
                    "name": "job5",
                    "value": 2000
                },
                {
                    "id": 6,
                    "name": "sales6",
                    "value": 300
                },
                {
                    "id": 7,
                    "name": "job7",
                    "value": 2000
                },
                {
                    "id": 8,
                    "name": "sales8",
                    "value": 300
                }
            ],
            "total": 2000
        },
        "stats": {
            "id": "2022-06-Stats",
            "available": 400,
            "withGoal": 300,
            "saved": 400,
            "goal": 45,
            "savings": 3000
        }
    }
]